Metadata-Version: 2.1
Name: very-simple-dictionary-egeergull
Version: 2.0.2
Summary: short package description
Author: Ege Ergül
Requires-Python: >=3.8
Requires-Dist: requests (>=2.23.0)
